ame_json/__init__.py
ame_json/logging_utils.py
ame_json/main.py
ame_json/models/__init__.py
ame_json/models/async_base_schema.py
ame_json/models/async_computation.py
ame_json/models/base_schema.py
ame_json/models/computation.py
ame_json/models/computation_utils.py
ame_json/models/path_data.py
ame_json/models/progressive_assembler.py
ame_json/models/progressive_schema.py
ame_json/models/progressive_streamer.py
ame_json/models/progressive_streamer_context.py
ame_json/models/utils.py
ame_json-0.1.0.dist-info/licenses/LICENSE
ame_json-0.1.0.dist-info/METADATA
ame_json-0.1.0.dist-info/WHEEL
ame_json-0.1.0.dist-info/top_level.txt
ame_json-0.1.0.dist-info/RECORD
