Metadata-Version: 2.4
Name: ame-json
Version: 0.1.0
Summary: Add your description here
Requires-Python: >=3.12
License-File: LICENSE
Requires-Dist: pydantic>=2.12.3
Dynamic: license-file
